altadb/__init__.py
altadb/config.py
altadb/dataset.py
altadb/py.typed
altadb/version_check.py
altadb/cli/__init__.py
altadb/cli/cli_base.py
altadb/cli/dataset.py
altadb/cli/public.py
altadb/cli/command/__init__.py
altadb/cli/command/config.py
altadb/cli/command/create.py
altadb/cli/command/export.py
altadb/cli/command/list.py
altadb/cli/command/query.py
altadb/cli/command/upload.py
altadb/cli/entity/__init__.py
altadb/cli/entity/cache.py
altadb/cli/entity/conf.py
altadb/cli/entity/creds.py
altadb/cli/input/__init__.py
altadb/cli/input/api_key.py
altadb/cli/input/api_secret.py
altadb/cli/input/number.py
altadb/cli/input/profile.py
altadb/cli/input/select.py
altadb/cli/input/text.py
altadb/cli/input/url.py
altadb/cli/input/uuid.py
altadb/common/__init__.py
altadb/common/client.py
altadb/common/constants.py
altadb/common/context.py
altadb/common/dataset.py
altadb/common/upload.py
altadb/export/__init__.py
altadb/export/public.py
altadb/organization/__init__.py
altadb/repo/__init__.py
altadb/repo/dataset.py
altadb/repo/upload.py
altadb/upload/__init__.py
altadb/upload/public.py
altadb/utils/__init__.py
altadb/utils/async_utils.py
altadb/utils/common_utils.py
altadb/utils/dicom_utils.py
altadb/utils/files.py
altadb/utils/logging.py
altadb/utils/pagination.py
altadb-0.0.6.dist-info/LICENSE
altadb-0.0.6.dist-info/METADATA
altadb-0.0.6.dist-info/WHEEL
altadb-0.0.6.dist-info/entry_points.txt
altadb-0.0.6.dist-info/top_level.txt
altadb-0.0.6.dist-info/RECORD
